MANIFEST.in
requirements.pip
setup.py
krux_boto/__init__.py
krux_boto.egg-info/PKG-INFO
krux_boto.egg-info/SOURCES.txt
krux_boto.egg-info/dependency_links.txt
krux_boto.egg-info/entry_points.txt
krux_boto.egg-info/requires.txt
krux_boto.egg-info/top_level.txt