Metadata-Version: 1.1
Name: krux-boto
Version: 0.0.4
Summary: Library for interacting with boto built on krux-stdlib
Home-page: https://github.com/krux/python-krux-boto
Author: Jos Boumans
Author-email: jos@krux.com
License: All Rights Reserved.
Download-URL: https://github.com/krux/python-krux-boto/tarball/release/0.0.4
Platform: UNKNOWN
